githush/__init__.py
githush/__main__.py
githush/cli.py
githush/config.py
githush/scan.py
githush-0.1.2.dist-info/METADATA
githush-0.1.2.dist-info/WHEEL
githush-0.1.2.dist-info/entry_points.txt
githush-0.1.2.dist-info/licenses/LICENSE
githush-0.1.2.dist-info/RECORD
