Metadata-Version: 2.4
Name: githush
Version: 0.1.2
Summary: A CLI tool to scan repositories for secrets
Author-email: Alessio Piccione <alessio.piccione@hotmail.it>
License: MIT
License-File: LICENSE
Requires-Python: >=3.12
Requires-Dist: click>=8.0
Requires-Dist: mypy>=1.15
Requires-Dist: pygit2>=1.17
Requires-Dist: pyyaml>=6.0
Provides-Extra: dev
Requires-Dist: pytest>=8.0; extra == 'dev'
Provides-Extra: lint
Requires-Dist: ruff>=0.11; extra == 'lint'
